{
  "main": {
    "id": "4aa7981108a4b322",
    "type": "split",
    "children": [
      {
        "id": "b1f83f93d334f0cf",
        "type": "tabs",
        "children": [
          {
            "id": "262dcbaacff72f1f",
            "type": "leaf",
            "state": {
              "type": "markdown",
              "state": {
                "file": "blog/2024-08-03-qsp-highlighting-docusaurus.md",
                "mode": "source",
                "source": false
              }
            }
          }
        ]
      }
    ],
    "direction": "vertical"
  },
  "left": {
    "id": "8293471c2c09a20b",
    "type": "split",
    "children": [
      {
        "id": "fae5b99d9b6ede4d",
        "type": "tabs",
        "children": [
          {
            "id": "61daad17fd4f3291",
            "type": "leaf",
            "state": {
              "type": "file-explorer",
              "state": {
                "sortOrder": "alphabetical"
              }
            }
          },
          {
            "id": "af9690975a0623c1",
            "type": "leaf",
            "state": {
              "type": "search",
              "state": {
                "query": "",
                "matchingCase": false,
                "explainSearch": false,
                "collapseAll": false,
                "extraContext": false,
                "sortOrder": "alphabetical"
              }
            }
          },
          {
            "id": "4b6e54ad6e0928a4",
            "type": "leaf",
            "state": {
              "type": "bookmarks",
              "state": {}
            }
          }
        ]
      }
    ],
    "direction": "horizontal",
    "width": 300
  },
  "right": {
    "id": "8ee93ae24e3030a7",
    "type": "split",
    "children": [
      {
        "id": "f02031b7f35d2026",
        "type": "tabs",
        "children": [
          {
            "id": "9eb541ac135ee62b",
            "type": "leaf",
            "state": {
              "type": "backlink",
              "state": {
                "file": "blog/2024-08-03-qsp-highlighting-docusaurus.md",
                "collapseAll": false,
                "extraContext": false,
                "sortOrder": "alphabetical",
                "showSearch": false,
                "searchQuery": "",
                "backlinkCollapsed": false,
                "unlinkedCollapsed": true
              }
            }
          },
          {
            "id": "242eca5547afdfa9",
            "type": "leaf",
            "state": {
              "type": "outgoing-link",
              "state": {
                "file": "blog/2024-08-03-qsp-highlighting-docusaurus.md",
                "linksCollapsed": false,
                "unlinkedCollapsed": true
              }
            }
          },
          {
            "id": "84ad4349a34d21dc",
            "type": "leaf",
            "state": {
              "type": "tag",
              "state": {
                "sortOrder": "frequency",
                "useHierarchy": true
              }
            }
          },
          {
            "id": "250902795cc88ac2",
            "type": "leaf",
            "state": {
              "type": "outline",
              "state": {
                "file": "blog/2024-08-03-qsp-highlighting-docusaurus.md"
              }
            }
          }
        ],
        "currentTab": 3
      }
    ],
    "direction": "horizontal",
    "width": 366.5
  },
  "left-ribbon": {
    "hiddenItems": {
      "switcher:Меню быстрого перехода": false,
      "graph:Граф": false,
      "canvas:Создать новый холст": false,
      "daily-notes:Сегодняшняя заметка": false,
      "templates:Вставить шаблон": false,
      "command-palette:Открыть палитру команд": false
    }
  },
  "active": "262dcbaacff72f1f",
  "lastOpenFiles": [
    "docs/articles/qspider_0120/index.md",
    "src/theme/toml-syntax/prism-toml.js",
    "src/theme/toml-syntax/prism-toml.js.opdownload",
    "src/theme/toml-syntax",
    "src/theme/Новая папка",
    "docs/articles/qspider_0120/images/8z8MHyp.png",
    "docs/articles/qspider_0120/images/image.png",
    "docs/articles/qspider_0120/images",
    "docs/articles/qspider_0120",
    "docs/articles/arrays_580/index.md",
    "docs/articles/arrays_580/images",
    "docs/articles/arrays_580",
    "docs/articles/arrays_580/images/N-Stg0hc-V1-U.jpg",
    "docs/informarch/updates/classic_to_570.md",
    "docs/informarch/updates/970_obnovlenie_do_5.7.0_0023.md",
    "docs/informarch/wii_qsp/info.md",
    "docs/informarch/wii_qsp/our_way.md",
    "docs/informarch/wii_qsp/short_faq.md",
    "docs/informarch/wii_qsp/003_nash_put.md",
    "docs/informarch/wii_qsp/002_informatsija_o_qsp.md",
    "docs/informarch/wii_qsp/001_faq_po_qsp.md",
    "docs/informarch/aeroqsp/guidebook.md",
    "docs/informarch/aeroqsp/wit/index.md",
    "docs/informarch/aeroqsp/wit/images",
    "docs/informarch/aeroqsp/wit",
    "docs/informarch/aeroqsp/wit/images/cityofmist.png",
    "docs/informarch/general/qgen_dev_guide/index.md",
    "docs/informarch/general/qgen_dev_guide/images/tut7-01.png",
    "docs/informarch/general/qgen_dev_guide/images/tut5-01.png",
    "docs/informarch/general/qgen_dev_guide/images/tut4-01.png",
    "docs/informarch/general/qgen_dev_guide/images/tut2-06.png",
    "docs/informarch/general/qgen_dev_guide/images/tut2-05.png",
    "docs/informarch/general/qgen_dev_guide/images/tut2-04.png",
    "docs/informarch/general/code_analyser.md",
    "docs/informarch/extrqsp/automat_programming/index.md",
    "docs/informarch/general/localization_classic_570.md",
    "docs/informarch/general/standalone_classic.md",
    "docs/informarch/general/game_shelf.md",
    "docs/informarch/txtgam/text_editor.md",
    "docs/informarch/txtgam/preprocessor.md",
    "docs/informarch/review/compo_2010.md",
    "docs/informarch/program/use_arrays.md",
    "docs/informarch/program/smooth_background.md",
    "docs/informarch/program/lib_flex_playlist.md",
    "docs/informarch/program/lib_extend_inventory.md",
    "docs/informarch/program/julian_calendar.md",
    "программирование/+Sublime Text/Модуль QSP.canvas",
    "программирование/+Sublime Text/QSP-plugin.canvas",
    "социальная психология/Без названия.canvas",
    "Без названия.canvas"
  ]
}